libfolder/__init__.py
libfolder/strtoamount.py
strtoamount-0.0.4.dist-info/METADATA
strtoamount-0.0.4.dist-info/WHEEL
strtoamount-0.0.4.dist-info/top_level.txt
strtoamount-0.0.4.dist-info/RECORD
